ai/__init__.py
ai/lzy/__init__.py
ai/lzy/v1/__init__.py
ai/lzy/v1/common/__init__.py
ai/lzy/v1/common/channel_pb2.py
ai/lzy/v1/common/channel_pb2_grpc.py
ai/lzy/v1/common/data_scheme_pb2.py
ai/lzy/v1/common/data_scheme_pb2_grpc.py
ai/lzy/v1/common/env_pb2.py
ai/lzy/v1/common/env_pb2_grpc.py
ai/lzy/v1/common/operation_pb2.py
ai/lzy/v1/common/operation_pb2_grpc.py
ai/lzy/v1/common/slot_pb2.py
ai/lzy/v1/common/slot_pb2_grpc.py
ai/lzy/v1/common/storage_pb2.py
ai/lzy/v1/common/storage_pb2_grpc.py
ai/lzy/v1/long_running/__init__.py
ai/lzy/v1/long_running/operation_pb2.py
ai/lzy/v1/long_running/operation_pb2_grpc.py
ai/lzy/v1/long_running/option_pb2.py
ai/lzy/v1/long_running/option_pb2_grpc.py
ai/lzy/v1/validation/__init__.py
ai/lzy/v1/validation/validation_pb2.py
ai/lzy/v1/validation/validation_pb2_grpc.py
ai/lzy/v1/whiteboard/__init__.py
ai/lzy/v1/whiteboard/whiteboard_pb2.py
ai/lzy/v1/whiteboard/whiteboard_pb2_grpc.py
ai/lzy/v1/whiteboard/whiteboard_service_pb2.py
ai/lzy/v1/whiteboard/whiteboard_service_pb2_grpc.py
ai/lzy/v1/workflow/__init__.py
ai/lzy/v1/workflow/workflow_pb2.py
ai/lzy/v1/workflow/workflow_pb2_grpc.py
ai/lzy/v1/workflow/workflow_private_service_pb2.py
ai/lzy/v1/workflow/workflow_private_service_pb2_grpc.py
ai/lzy/v1/workflow/workflow_service_pb2.py
ai/lzy/v1/workflow/workflow_service_pb2_grpc.py
lzy/__init__.py
lzy/config.py
lzy/exceptions.py
lzy/types.py
lzy/version.py
lzy/api/__init__.py
lzy/api/v1/__init__.py
lzy/api/v1/call.py
lzy/api/v1/entry_index.py
lzy/api/v1/env.py
lzy/api/v1/exceptions.py
lzy/api/v1/provisioning.py
lzy/api/v1/runtime.py
lzy/api/v1/signatures.py
lzy/api/v1/snapshot.py
lzy/api/v1/startup.py
lzy/api/v1/whiteboards.py
lzy/api/v1/workflow.py
lzy/api/v1/local/__init__.py
lzy/api/v1/local/runtime.py
lzy/api/v1/remote/__init__.py
lzy/api/v1/remote/lzy_service_client.py
lzy/api/v1/remote/runtime.py
lzy/api/v1/remote/model/__init__.py
lzy/api/v1/remote/model/converter/__init__.py
lzy/api/v1/remote/model/converter/storage_creds.py
pylzy-1.14.0.dist-info/LICENSE
pylzy-1.14.0.dist-info/METADATA
pylzy-1.14.0.dist-info/WHEEL
pylzy-1.14.0.dist-info/top_level.txt
pylzy-1.14.0.dist-info/RECORD
