Metadata-Version: 2.1
Name: pylzy
Version: 1.14.0
Author: ʎzy developers
License: Apache-2.0
Classifier: Programming Language :: Python :: 3.8
Classifier: Programming Language :: Python :: 3.9
Classifier: Programming Language :: Python :: 3.10
Classifier: Programming Language :: Python :: 3.11
Classifier: License :: OSI Approved :: Apache Software License
Requires-Python: >=3.8
License-File: LICENSE
Requires-Dist: aioboto3 (>=9.6.0)
Requires-Dist: appdirs (<2.0.0,>=1.4.4)
Requires-Dist: azure-storage-blob (<13.0.0,>=12.9.0)
Requires-Dist: beartype (<1.0.0,>=0.10.0)
Requires-Dist: botocore (>=1.27.59)
Requires-Dist: cloudpickle (<3.0.0,>=2.1.0)
Requires-Dist: grpcio (>=1.46.0)
Requires-Dist: googleapis-common-protos (>=1.56.3)
Requires-Dist: importlib-metadata (>=4.8.1)
Requires-Dist: packaging (>=21.3.0)
Requires-Dist: pip (>=10.0)
Requires-Dist: protobuf (>=4.21.1)
Requires-Dist: pycryptodome (<4.0.0,>=3.15.0)
Requires-Dist: pyjwt[crypto] (<3.0.0,>=2.4.0)
Requires-Dist: pypi-simple (<2.0.0,>=1.1.0)
Requires-Dist: pyyaml (<7.0.0,>=6.0.0)
Requires-Dist: requests (<3.0.0,>=2.26.0)
Requires-Dist: serialzy (<2.0.0,>=1.2.0)
Requires-Dist: tqdm (<5.0.0,>=4.64.0)
Requires-Dist: typing-extensions (>=4.4.0)
Requires-Dist: stdlib-list (<1.0.0,>=0.8.0) ; python_version < "3.10"
